[
  {
    "id": 1,
    "category": "Ceramic Products",
    "description": "High-quality ceramic tiles.",
    "image": "/images/categories/ceramic_products.jpg",
    "subcategories": [
      {
        "id": 101,
        "subcategory": "Floor Tiles",
        "description": "Trendy ceramic floor tiles in various dimensions.",
        "image": "/images/subcategories/floor_tiles.jpg",
        "options": [
          {
            "id": 1011,
            "dimension": "300x300",
            "image": "/logo.png",
            "link": "https://drive.google.com/drive/folders/1r3J2BzepGASKBagO6-5qiNDvbN0ev8lr"
          },
          {
            "id": 1012,
            "dimension": "400x400",
            "image": "/images/options/floor_tile_400x400.jpg",
            "link": "https://drive.google.com/drive/folders/1PUMHQZRCghfE7xIkz8txUA5wUdcC7O3x"
          },
          {
            "id": 1013,
            "dimension": "500x500",
            "image": "/images/options/floor_tile_600x600.jpg",
            "link": "https://drive.google.com/drive/folders/1jtBX1yyvOn-U40RGfB9ZvgWbwpXGGag1"
          },
          {
            "id": 1014,
            "dimension": "600x600 Porcelain",
            "image": "/logo.png",
            "link": "https://drive.google.com/drive/folders/14Nh6cJ1pXcCnLZMaNTZ6bNBvAXDq62MJ"
          },
          {
            "id": 1015,
            "dimension": "600x600 Double Charge",
            "image": "/images/options/floor_tile_400x400.jpg",
            "link": "https://drive.google.com/drive/folders/1Yokup9Yr7QU1LI6Pksfi9cKrf4q52pmm"
          },
          {
            "id": 1016,
            "dimension": "600x600 Vitrified",
            "image": "/images/options/floor_tile_600x600.jpg",
            "link": "https://drive.google.com/drive/folders/1QqT4ZeAJFOt2wSVFSRzAXBS3UQjfXt-Z"
          },
          {
            "id": 1017,
            "dimension": "600x1200",
            "image": "/logo.png",
            "link": "https://drive.google.com/drive/folders/1xr5XGSlirlLmcT0jonIdC0QLxsUnVEr0"
          },
          {
            "id": 1018,
            "dimension": "800x800 Double Charge",
            "image": "/images/options/floor_tile_400x400.jpg",
            "link": "https://drive.google.com/drive/folders/1JnQNr0bgiyfLWxVnK0bf_dC67ZeSmr5T"
          },
          {
            "id": 1019,
            "dimension": "800x800 Porcelain",
            "image": "/images/options/floor_tile_600x600.jpg",
            "link": "https://drive.google.com/drive/folders/1yxKBS0gubgcFcL3A2znoBnuJhJeGtEjF"
          },
          {
            "id": 10110,
            "dimension": "800x1600",
            "image": "/logo.png",
            "link": "https://drive.google.com/drive/folders/14hG36KonrIt3U07i7AnS3L9jAFY9aLBw"
          },
          {
            "id": 10111,
            "dimension": "1200x1200",
            "image": "/images/options/floor_tile_400x400.jpg",
            "link": "https://drive.google.com/drive/folders/1Pil-rsyiPf_x9jo3KU7V9qAobTv4EjHm"
          },
          {
            "id": 10112,
            "dimension": "1200x1800",
            "image": "/images/options/floor_tile_600x600.jpg",
            "link": "https://drive.google.com/drive/folders/19et3AXOV65aAu4Wnah7rO3Nud6w8r9PK"
          },
          {
            "id": 10113,
            "dimension": "1200x2400",
            "image": "/images/options/floor_tile_400x400.jpg",
            "link": "https://drive.google.com/drive/folders/1pBpv0aO-RyKPxFEtaDItpDiC8qUgG6_p"
          },
          {
            "id": 10114,
            "dimension": "800x2400",
            "image": "/images/options/floor_tile_600x600.jpg",
            "link": "https://drive.google.com/drive/folders/1TYFBjAUY9chvYNACn5B0YNjoML6eU196"
          },
          {
            "id": 10115,
            "dimension": "800x3000",
            "image": "/logo.png",
            "link": "https://drive.google.com/drive/folders/1cz4vHfnDWw2r71QEtJeav41kDPT1nx3H"
          },
          {
            "id": 10116,
            "dimension": "1200x200",
            "image": "/images/options/floor_tile_400x400.jpg",
            "link": "https://drive.google.com/drive/folders/1ZAIFk1r8Iny-YRNCKSAuO2W7Y9XXFl5R"
          },
          {
            "id": 10117,
            "dimension": "600x600 Full body",
            "image": "/images/options/floor_tile_600x600.jpg",
            "link": "https://drive.google.com/drive/folders/1jQGctkHjF-k7atJdNm4DfTyj3sgqDyF-"
          }
        ]
      },
      {
        "id": 102,
        "subcategory": "Wall Tiles",
        "description": "Stylish wall tiles to enhance your interiors.",
        "image": "/images/subcategories/wall_tiles.jpg",
        "options": [
          {
            "id": 1021,
            "dimension": "200x300",
            "image": "/images/options/wall_tile_300x600.jpg",
            "link": "https://drive.google.com/drive/folders/1qv7deZhSkDTOzW5fe9_Kpevfc1s7CEcr"
          },
          {
            "id": 1022,
            "dimension": "200x600",
            "image": "/images/options/wall_tile_600x1200.jpg",
            "link": "https://example.com/download/105"
          },
          {
            "id": 1023,
            "dimension": "250x375",
            "image": "/images/options/wall_tile_600x1200.jpg",
            "link": "https://example.com/download/105"
          },
          {
            "id": 1024,
            "dimension": "250x400",
            "image": "/images/options/wall_tile_600x1200.jpg",
            "link": "https://example.com/download/105"
          },
          {
            "id": 1025,
            "dimension": "300x450 High depth",
            "image": "/images/options/wall_tile_600x1200.jpg",
            "link": "https://example.com/download/105"
          },
          {
            "id": 1026,
            "dimension": "300x450",
            "image": "/images/options/wall_tile_600x1200.jpg",
            "link": "https://example.com/download/105"
          },
          {
            "id": 1027,
            "dimension": "300x600 Digital",
            "image": "/images/options/wall_tile_600x1200.jpg",
            "link": "https://example.com/download/105"
          },
          {
            "id": 1028,
            "dimension": "300x600 Porceline wall",
            "image": "/images/options/wall_tile_600x1200.jpg",
            "link": "https://example.com/download/105"
          },
          {
            "id": 1029,
            "dimension": "300x600 #rd Firing tiles",
            "image": "/images/options/wall_tile_600x1200.jpg",
            "link": "https://example.com/download/105"
          },
          {
            "id": 1030,
            "dimension": "300x600 High depth",
            "image": "/images/options/wall_tile_600x1200.jpg",
            "link": "https://example.com/download/105"
          }

        ]
      },
      {
        "id": 103,
        "subcategory": "Parking Tiles",
        "description": "Durable tiles designed for parking spaces.",
        "image": "/images/subcategories/parking_tiles.jpg",
        "options": [
          {
            "id": 1031,
            "dimension": "400x400",
            "image": "/images/options/parking_tile_400x400.jpg",
            "link": "https://example.com/download/106"
          },
          {
            "id": 1032,
            "dimension": "300x300",
            "image": "/images/options/parking_tile_600x600.jpg",
            "link": "https://example.com/download/107"
          }
        ]
      },
      {
        "id": 104,
        "subcategory": "Roof Tiles",
        "description": "Elegant and durable roof tiles.",
        "image": "/images/subcategories/roof_tiles.jpg"     
      },
      {
        "id": 105,
        "subcategory": "Subway Tiles",
        "description": "Elegant and durable roof tiles.",
        "image": "/images/subcategories/roof_tiles.jpg"
      },
      {
        "id": 106,
        "subcategory": "Step Riser",
        "description": "Elegant and durable roof tiles.",
        "image": "/images/subcategories/roof_tiles.jpg",
        "options": [
          {
            "id": 1061,
            "dimension": "5 feet step Riser",
            "image": "/images/options/roof_tile_400x400.jpg",
            "link": "https://example.com/download/108"
          },
          {
            "id": 1062,
            "dimension": "4 feet step Riser",
            "image": "/images/options/roof_tile_400x400.jpg",
            "link": "https://example.com/download/108"
          },
          {
            "id": 1063,
            "dimension": "3 feet step Riser",
            "image": "/images/options/roof_tile_400x400.jpg",
            "link": "https://example.com/download/108"
          }
        ]
      },
      {
        "id": 107,
        "subcategory": "Poster & Decoretive tiles",
        "description": "Elegant and durable roof tiles.",
        "image": "/images/subcategories/roof_tiles.jpg"
      }
    ]
  },
  {
    "id": 2,
    "category": "Sanitaryware",
    "description": "Premium sanitary products for your bathrooms.",
    "image": "/images/categories/sanitaryware.jpg",
    "subcategories": [
      {
        "id": 201,
        "subcategory": "Wash Basins",
        "description": "Stylish and functional wash basins.",
        "image": "/images/subcategories/wash_basins.jpg",
        "options": [
          {
            "id": 2011,
            "dimension": "Standard Size",
            "image": "/images/options/wash_basin_standard.jpg",
            "link": "https://example.com/download/109"
          },
          {
            "id": 2012,
            "dimension": "Compact Size",
            "image": "/images/options/wash_basin_compact.jpg",
            "link": "https://example.com/download/110"
          }
        ]
      },
      {
        "id": 202,
        "subcategory": "Toilets",
        "description": "High-quality ceramic toilets.",
        "image": "/images/subcategories/toilets.jpg",
        "options": [
          {
            "id": 2021,
            "dimension": "Modern Design",
            "image": "/images/options/toilet_modern.jpg",
            "link": "https://example.com/download/111"
          },
          {
            "id": 2022,
            "dimension": "Classic Design",
            "image": "/images/options/toilet_classic.jpg",
            "link": "https://example.com/download/112"
          }
        ]
      }
    ]
  }
]
